{
  "id": "b575d65d-eae3-41a8-a649-5efcdddb85e8",
  "prevId": "a1b2c3d4-5678-90ab-cdef-1234567890ab",
  "version": "7",
  "dialect": "postgresql",
  "tables": {
    "public.chapter_progress": {
      "name": "chapter_progress",
      "schema": "",
      "columns": {
        "id": {
          "name": "id",
          "type": "serial",
          "primaryKey": true,
          "notNull": true
        },
        "student_id": {
          "name": "student_id",
          "type": "integer",
          "primaryKey": false,
          "notNull": false
        },
        "chapter_id": {
          "name": "chapter_id",
          "type": "integer",
          "primaryKey": false,
          "notNull": false
        },
        "completed_at": {
          "name": "completed_at",
          "type": "timestamp",
          "primaryKey": false,
          "notNull": false,
          "default": "now()"
        }
      },
      "indexes": {},
      "foreignKeys": {
        "chapter_progress_student_id_users_id_fk": {
          "name": "chapter_progress_student_id_users_id_fk",
          "tableFrom": "chapter_progress",
          "tableTo": "users",
          "columnsFrom": [
            "student_id"
          ],
          "columnsTo": [
            "id"
          ],
          "onDelete": "no action",
          "onUpdate": "no action"
        },
        "chapter_progress_chapter_id_chapters_id_fk": {
          "name": "chapter_progress_chapter_id_chapters_id_fk",
          "tableFrom": "chapter_progress",
          "tableTo": "chapters",
          "columnsFrom": [
            "chapter_id"
          ],
          "columnsTo": [
            "id"
          ],
          "onDelete": "no action",
          "onUpdate": "no action"
        }
      },
      "compositePrimaryKeys": {},
      "uniqueConstraints": {},
      "policies": {},
      "checkConstraints": {},
      "isRLSEnabled": false
    },
    "public.chapters": {
      "name": "chapters",
      "schema": "",
      "columns": {
        "id": {
          "name": "id",
          "type": "serial",
          "primaryKey": true,
          "notNull": true
        },
        "course_id": {
          "name": "course_id",
          "type": "integer",
          "primaryKey": false,
          "notNull": false
        },
        "title": {
          "name": "title",
          "type": "varchar(200)",
          "primaryKey": false,
          "notNull": true
        },
        "description": {
          "name": "description",
          "type": "text",
          "primaryKey": false,
          "notNull": false
        },
        "order_index": {
          "name": "order_index",
          "type": "integer",
          "primaryKey": false,
          "notNull": true
        },
        "content_type": {
          "name": "content_type",
          "type": "varchar(20)",
          "primaryKey": false,
          "notNull": true
        },
        "content_data": {
          "name": "content_data",
          "type": "jsonb",
          "primaryKey": false,
          "notNull": true
        },
        "created_at": {
          "name": "created_at",
          "type": "timestamp",
          "primaryKey": false,
          "notNull": false,
          "default": "now()"
        }
      },
      "indexes": {},
      "foreignKeys": {
        "chapters_course_id_courses_id_fk": {
          "name": "chapters_course_id_courses_id_fk",
          "tableFrom": "chapters",
          "tableTo": "courses",
          "columnsFrom": [
            "course_id"
          ],
          "columnsTo": [
            "id"
          ],
          "onDelete": "no action",
          "onUpdate": "no action"
        }
      },
      "compositePrimaryKeys": {},
      "uniqueConstraints": {},
      "policies": {},
      "checkConstraints": {},
      "isRLSEnabled": false
    },
    "public.courses": {
      "name": "courses",
      "schema": "",
      "columns": {
        "id": {
          "name": "id",
          "type": "serial",
          "primaryKey": true,
          "notNull": true
        },
        "title": {
          "name": "title",
          "type": "varchar(255)",
          "primaryKey": false,
          "notNull": true
        },
        "description": {
          "name": "description",
          "type": "text",
          "primaryKey": false,
          "notNull": false
        },
        "domain_id": {
          "name": "domain_id",
          "type": "integer",
          "primaryKey": false,
          "notNull": false
        },
        "teacher_id": {
          "name": "teacher_id",
          "type": "integer",
          "primaryKey": false,
          "notNull": false
        },
        "thumbnail_url": {
          "name": "thumbnail_url",
          "type": "text",
          "primaryKey": false,
          "notNull": false
        },
        "is_active": {
          "name": "is_active",
          "type": "boolean",
          "primaryKey": false,
          "notNull": false,
          "default": true
        },
        "created_at": {
          "name": "created_at",
          "type": "timestamp",
          "primaryKey": false,
          "notNull": true,
          "default": "now()"
        },
        "updated_at": {
          "name": "updated_at",
          "type": "timestamp",
          "primaryKey": false,
          "notNull": true,
          "default": "now()"
        }
      },
      "indexes": {},
      "foreignKeys": {
        "courses_domain_id_domains_id_fk": {
          "name": "courses_domain_id_domains_id_fk",
          "tableFrom": "courses",
          "tableTo": "domains",
          "columnsFrom": [
            "domain_id"
          ],
          "columnsTo": [
            "id"
          ],
          "onDelete": "no action",
          "onUpdate": "no action"
        },
        "courses_teacher_id_users_id_fk": {
          "name": "courses_teacher_id_users_id_fk",
          "tableFrom": "courses",
          "tableTo": "users",
          "columnsFrom": [
            "teacher_id"
          ],
          "columnsTo": [
            "id"
          ],
          "onDelete": "no action",
          "onUpdate": "no action"
        }
      },
      "compositePrimaryKeys": {},
      "uniqueConstraints": {},
      "policies": {},
      "checkConstraints": {},
      "isRLSEnabled": false
    },
    "public.domains": {
      "name": "domains",
      "schema": "",
      "columns": {
        "id": {
          "name": "id",
          "type": "serial",
          "primaryKey": true,
          "notNull": true
        },
        "name": {
          "name": "name",
          "type": "varchar(100)",
          "primaryKey": false,
          "notNull": true
        },
        "description": {
          "name": "description",
          "type": "text",
          "primaryKey": false,
          "notNull": false
        },
        "color": {
          "name": "color",
          "type": "varchar(7)",
          "primaryKey": false,
          "notNull": false,
          "default": "'#6366f1'"
        },
        "created_at": {
          "name": "created_at",
          "type": "timestamp",
          "primaryKey": false,
          "notNull": false,
          "default": "now()"
        }
      },
      "indexes": {},
      "foreignKeys": {},
      "compositePrimaryKeys": {},
      "uniqueConstraints": {},
      "policies": {},
      "checkConstraints": {},
      "isRLSEnabled": false
    },
    "public.enrollments": {
      "name": "enrollments",
      "schema": "",
      "columns": {
        "id": {
          "name": "id",
          "type": "serial",
          "primaryKey": true,
          "notNull": true
        },
        "student_id": {
          "name": "student_id",
          "type": "integer",
          "primaryKey": false,
          "notNull": false
        },
        "course_id": {
          "name": "course_id",
          "type": "integer",
          "primaryKey": false,
          "notNull": false
        },
        "completed_at": {
          "name": "completed_at",
          "type": "timestamp",
          "primaryKey": false,
          "notNull": false
        },
        "created_at": {
          "name": "created_at",
          "type": "timestamp",
          "primaryKey": false,
          "notNull": true,
          "default": "now()"
        },
        "updated_at": {
          "name": "updated_at",
          "type": "timestamp",
          "primaryKey": false,
          "notNull": true,
          "default": "now()"
        }
      },
      "indexes": {},
      "foreignKeys": {
        "enrollments_student_id_users_id_fk": {
          "name": "enrollments_student_id_users_id_fk",
          "tableFrom": "enrollments",
          "tableTo": "users",
          "columnsFrom": [
            "student_id"
          ],
          "columnsTo": [
            "id"
          ],
          "onDelete": "no action",
          "onUpdate": "no action"
        },
        "enrollments_course_id_courses_id_fk": {
          "name": "enrollments_course_id_courses_id_fk",
          "tableFrom": "enrollments",
          "tableTo": "courses",
          "columnsFrom": [
            "course_id"
          ],
          "columnsTo": [
            "id"
          ],
          "onDelete": "no action",
          "onUpdate": "no action"
        }
      },
      "compositePrimaryKeys": {},
      "uniqueConstraints": {},
      "policies": {},
      "checkConstraints": {},
      "isRLSEnabled": false
    },
    "public.final_projects": {
      "name": "final_projects",
      "schema": "",
      "columns": {
        "id": {
          "name": "id",
          "type": "serial",
          "primaryKey": true,
          "notNull": true
        },
        "course_id": {
          "name": "course_id",
          "type": "integer",
          "primaryKey": false,
          "notNull": false
        },
        "title": {
          "name": "title",
          "type": "varchar(200)",
          "primaryKey": false,
          "notNull": true
        },
        "description": {
          "name": "description",
          "type": "text",
          "primaryKey": false,
          "notNull": true
        },
        "requirements": {
          "name": "requirements",
          "type": "jsonb",
          "primaryKey": false,
          "notNull": false
        },
        "created_at": {
          "name": "created_at",
          "type": "timestamp",
          "primaryKey": false,
          "notNull": false,
          "default": "now()"
        }
      },
      "indexes": {},
      "foreignKeys": {
        "final_projects_course_id_courses_id_fk": {
          "name": "final_projects_course_id_courses_id_fk",
          "tableFrom": "final_projects",
          "tableTo": "courses",
          "columnsFrom": [
            "course_id"
          ],
          "columnsTo": [
            "id"
          ],
          "onDelete": "no action",
          "onUpdate": "no action"
        }
      },
      "compositePrimaryKeys": {},
      "uniqueConstraints": {},
      "policies": {},
      "checkConstraints": {},
      "isRLSEnabled": false
    },
    "public.project_submissions": {
      "name": "project_submissions",
      "schema": "",
      "columns": {
        "id": {
          "name": "id",
          "type": "serial",
          "primaryKey": true,
          "notNull": true
        },
        "student_id": {
          "name": "student_id",
          "type": "integer",
          "primaryKey": false,
          "notNull": false
        },
        "final_project_id": {
          "name": "final_project_id",
          "type": "integer",
          "primaryKey": false,
          "notNull": false
        },
        "submission_url": {
          "name": "submission_url",
          "type": "text",
          "primaryKey": false,
          "notNull": false
        },
        "description": {
          "name": "description",
          "type": "text",
          "primaryKey": false,
          "notNull": false
        },
        "status": {
          "name": "status",
          "type": "varchar(20)",
          "primaryKey": false,
          "notNull": false,
          "default": "'submitted'"
        },
        "feedback": {
          "name": "feedback",
          "type": "text",
          "primaryKey": false,
          "notNull": false
        },
        "grade": {
          "name": "grade",
          "type": "integer",
          "primaryKey": false,
          "notNull": false
        },
        "submitted_at": {
          "name": "submitted_at",
          "type": "timestamp",
          "primaryKey": false,
          "notNull": false,
          "default": "now()"
        },
        "reviewed_at": {
          "name": "reviewed_at",
          "type": "timestamp",
          "primaryKey": false,
          "notNull": false
        }
      },
      "indexes": {},
      "foreignKeys": {
        "project_submissions_student_id_users_id_fk": {
          "name": "project_submissions_student_id_users_id_fk",
          "tableFrom": "project_submissions",
          "tableTo": "users",
          "columnsFrom": [
            "student_id"
          ],
          "columnsTo": [
            "id"
          ],
          "onDelete": "no action",
          "onUpdate": "no action"
        },
        "project_submissions_final_project_id_final_projects_id_fk": {
          "name": "project_submissions_final_project_id_final_projects_id_fk",
          "tableFrom": "project_submissions",
          "tableTo": "final_projects",
          "columnsFrom": [
            "final_project_id"
          ],
          "columnsTo": [
            "id"
          ],
          "onDelete": "no action",
          "onUpdate": "no action"
        }
      },
      "compositePrimaryKeys": {},
      "uniqueConstraints": {},
      "policies": {},
      "checkConstraints": {},
      "isRLSEnabled": false
    },
    "public.quiz_attempts": {
      "name": "quiz_attempts",
      "schema": "",
      "columns": {
        "id": {
          "name": "id",
          "type": "serial",
          "primaryKey": true,
          "notNull": true
        },
        "student_id": {
          "name": "student_id",
          "type": "integer",
          "primaryKey": false,
          "notNull": false
        },
        "quiz_id": {
          "name": "quiz_id",
          "type": "integer",
          "primaryKey": false,
          "notNull": false
        },
        "answers": {
          "name": "answers",
          "type": "jsonb",
          "primaryKey": false,
          "notNull": true
        },
        "score": {
          "name": "score",
          "type": "integer",
          "primaryKey": false,
          "notNull": true
        },
        "passed": {
          "name": "passed",
          "type": "boolean",
          "primaryKey": false,
          "notNull": true
        },
        "attempted_at": {
          "name": "attempted_at",
          "type": "timestamp",
          "primaryKey": false,
          "notNull": false,
          "default": "now()"
        }
      },
      "indexes": {},
      "foreignKeys": {
        "quiz_attempts_student_id_users_id_fk": {
          "name": "quiz_attempts_student_id_users_id_fk",
          "tableFrom": "quiz_attempts",
          "tableTo": "users",
          "columnsFrom": [
            "student_id"
          ],
          "columnsTo": [
            "id"
          ],
          "onDelete": "no action",
          "onUpdate": "no action"
        },
        "quiz_attempts_quiz_id_quizzes_id_fk": {
          "name": "quiz_attempts_quiz_id_quizzes_id_fk",
          "tableFrom": "quiz_attempts",
          "tableTo": "quizzes",
          "columnsFrom": [
            "quiz_id"
          ],
          "columnsTo": [
            "id"
          ],
          "onDelete": "no action",
          "onUpdate": "no action"
        }
      },
      "compositePrimaryKeys": {},
      "uniqueConstraints": {},
      "policies": {},
      "checkConstraints": {},
      "isRLSEnabled": false
    },
    "public.quizzes": {
      "name": "quizzes",
      "schema": "",
      "columns": {
        "id": {
          "name": "id",
          "type": "serial",
          "primaryKey": true,
          "notNull": true
        },
        "chapter_id": {
          "name": "chapter_id",
          "type": "integer",
          "primaryKey": false,
          "notNull": false
        },
        "title": {
          "name": "title",
          "type": "varchar(200)",
          "primaryKey": false,
          "notNull": true
        },
        "questions": {
          "name": "questions",
          "type": "jsonb",
          "primaryKey": false,
          "notNull": true
        },
        "passing_score": {
          "name": "passing_score",
          "type": "integer",
          "primaryKey": false,
          "notNull": false,
          "default": 70
        },
        "created_at": {
          "name": "created_at",
          "type": "timestamp",
          "primaryKey": false,
          "notNull": true,
          "default": "now()"
        }
      },
      "indexes": {},
      "foreignKeys": {
        "quizzes_chapter_id_chapters_id_fk": {
          "name": "quizzes_chapter_id_chapters_id_fk",
          "tableFrom": "quizzes",
          "tableTo": "chapters",
          "columnsFrom": [
            "chapter_id"
          ],
          "columnsTo": [
            "id"
          ],
          "onDelete": "no action",
          "onUpdate": "no action"
        }
      },
      "compositePrimaryKeys": {},
      "uniqueConstraints": {},
      "policies": {},
      "checkConstraints": {},
      "isRLSEnabled": false
    },
    "public.users": {
      "name": "users",
      "schema": "",
      "columns": {
        "id": {
          "name": "id",
          "type": "serial",
          "primaryKey": true,
          "notNull": true
        },
        "email": {
          "name": "email",
          "type": "varchar(255)",
          "primaryKey": false,
          "notNull": true
        },
        "password": {
          "name": "password",
          "type": "varchar(255)",
          "primaryKey": false,
          "notNull": true
        },
        "name": {
          "name": "name",
          "type": "varchar(255)",
          "primaryKey": false,
          "notNull": true
        },
        "role": {
          "name": "role",
          "type": "role",
          "typeSchema": "public",
          "primaryKey": false,
          "notNull": true,
          "default": "'STUDENT'"
        },
        "avatar_url": {
          "name": "avatar_url",
          "type": "varchar(500)",
          "primaryKey": false,
          "notNull": false
        },
        "is_active": {
          "name": "is_active",
          "type": "boolean",
          "primaryKey": false,
          "notNull": false,
          "default": true
        },
        "phone": {
          "name": "phone",
          "type": "varchar(20)",
          "primaryKey": false,
          "notNull": false
        },
        "date_of_birth": {
          "name": "date_of_birth",
          "type": "timestamp",
          "primaryKey": false,
          "notNull": false
        },
        "address": {
          "name": "address",
          "type": "text",
          "primaryKey": false,
          "notNull": false
        },
        "city": {
          "name": "city",
          "type": "varchar(100)",
          "primaryKey": false,
          "notNull": false
        },
        "postal_code": {
          "name": "postal_code",
          "type": "varchar(20)",
          "primaryKey": false,
          "notNull": false
        },
        "country": {
          "name": "country",
          "type": "varchar(100)",
          "primaryKey": false,
          "notNull": false,
          "default": "'Morocco'"
        },
        "emergency_contact_name": {
          "name": "emergency_contact_name",
          "type": "varchar(255)",
          "primaryKey": false,
          "notNull": false
        },
        "emergency_contact_phone": {
          "name": "emergency_contact_phone",
          "type": "varchar(20)",
          "primaryKey": false,
          "notNull": false
        },
        "education_level": {
          "name": "education_level",
          "type": "varchar(100)",
          "primaryKey": false,
          "notNull": false
        },
        "institution": {
          "name": "institution",
          "type": "varchar(255)",
          "primaryKey": false,
          "notNull": false
        },
        "bio": {
          "name": "bio",
          "type": "text",
          "primaryKey": false,
          "notNull": false
        },
        "consent_timestamp": {
          "name": "consent_timestamp",
          "type": "timestamp",
          "primaryKey": false,
          "notNull": false
        },
        "created_at": {
          "name": "created_at",
          "type": "timestamp",
          "primaryKey": false,
          "notNull": true,
          "default": "now()"
        },
        "updated_at": {
          "name": "updated_at",
          "type": "timestamp",
          "primaryKey": false,
          "notNull": true,
          "default": "now()"
        }
      },
      "indexes": {},
      "foreignKeys": {},
      "compositePrimaryKeys": {},
      "uniqueConstraints": {
        "users_email_unique": {
          "name": "users_email_unique",
          "nullsNotDistinct": false,
          "columns": [
            "email"
          ]
        }
      },
      "policies": {},
      "checkConstraints": {},
      "isRLSEnabled": false
    }
  },
  "enums": {
    "public.course_status": {
      "name": "course_status",
      "schema": "public",
      "values": [
        "draft",
        "validated"
      ]
    },
    "public.quiz_type": {
      "name": "quiz_type",
      "schema": "public",
      "values": [
        "auto",
        "manual"
      ]
    },
    "public.role": {
      "name": "role",
      "schema": "public",
      "values": [
        "STUDENT",
        "TRAINER",
        "SUB_ADMIN",
        "ADMIN"
      ]
    }
  },
  "schemas": {},
  "sequences": {},
  "roles": {},
  "policies": {},
  "views": {},
  "_meta": {
    "columns": {},
    "schemas": {},
    "tables": {}
  }
}